[
  {
    "timestamp": "2025-06-28T19:57:45.849Z",
    "originalMessageId": "false_972507735297@c.us_3FFC8E0AB81663F0032B",
    "generatedFilePath": "C:\\Users\\hillel1\\Desktop\\WHAT\\chats/972507735297_דיצה/files/false_972507735297@c.us_3FFC8E0AB81663F0032B.jpeg",
    "filename": "false_972507735297@c.us_3FFC8E0AB81663F0032B.jpeg",
    "description": "קובץ מדיה שהתקבל מהמשתמש (דיצה)",
    "type": "image/jpeg"
  },
  {
    "timestamp": "2025-06-28T19:57:45.852Z",
    "originalMessageId": "false_972507735297@c.us_3F05A9838F90EDC26DBD",
    "generatedFilePath": "C:\\Users\\hillel1\\Desktop\\WHAT\\chats/972507735297_דיצה/files/false_972507735297@c.us_3F05A9838F90EDC26DBD.jpeg",
    "filename": "false_972507735297@c.us_3F05A9838F90EDC26DBD.jpeg",
    "description": "קובץ מדיה שהתקבל מהמשתמש (דיצה)",
    "type": "image/jpeg"
  },
  {
    "timestamp": "2025-06-28T19:57:46.078Z",
    "originalMessageId": "false_972507735297@c.us_3FA519F879FDE7411BF3",
    "generatedFilePath": "C:\\Users\\hillel1\\Desktop\\WHAT\\chats/972507735297_דיצה/files/false_972507735297@c.us_3FA519F879FDE7411BF3.jpeg",
    "filename": "false_972507735297@c.us_3FA519F879FDE7411BF3.jpeg",
    "description": "קובץ מדיה שהתקבל מהמשתמש (דיצה)",
    "type": "image/jpeg"
  },
  {
    "timestamp": "2025-06-30T10:17:08.782Z",
    "originalMessageId": "true_972507735297@c.us_65F8EB575F2571FED1A674DD7AA03BB1",
    "generatedFilePath": "C:\\Users\\hillel1\\Desktop\\WHAT\\chats/972507735297_דיצה/files/true_972507735297@c.us_65F8EB575F2571FED1A674DD7AA03BB1.jpeg",
    "filename": "true_972507735297@c.us_65F8EB575F2571FED1A674DD7AA03BB1.jpeg",
    "description": "קובץ מדיה שהתקבל מהמשתמש (הלל (Owner))",
    "type": "image/jpeg"
  },
  {
    "timestamp": "2025-06-30T10:59:18.626Z",
    "originalMessageId": "true_972507735297@c.us_3FC8A3CDA8B79D3E8E71",
    "generatedFilePath": "C:\\Users\\hillel1\\Desktop\\WHAT\\chats/972507735297_דיצה/files/true_972507735297@c.us_3FC8A3CDA8B79D3E8E71.jpeg",
    "filename": "true_972507735297@c.us_3FC8A3CDA8B79D3E8E71.jpeg",
    "description": "קובץ מדיה שהתקבל מהמשתמש (הלל (Owner))",
    "type": "image/jpeg"
  },
  {
    "timestamp": "2025-07-01T20:11:58.172Z",
    "originalMessageId": "false_972507735297@c.us_3F3BBD0D027BAEBAED51",
    "generatedFilePath": "C:\\Users\\hillel1\\Desktop\\WHAT\\chats/972507735297_דיצה/files/false_972507735297@c.us_3F3BBD0D027BAEBAED51.jpeg",
    "filename": "false_972507735297@c.us_3F3BBD0D027BAEBAED51.jpeg",
    "description": "קובץ מדיה שהתקבל מהמשתמש (דיצה)",
    "type": "image/jpeg"
  },
  {
    "timestamp": "2025-07-01T20:15:27.692Z",
    "originalMessageId": "false_972507735297@c.us_DAD4FA7BAF0BF546398F15F8F2941C96",
    "generatedFilePath": "C:\\Users\\hillel1\\Desktop\\WHAT\\chats/972507735297_דיצה/files/false_972507735297@c.us_DAD4FA7BAF0BF546398F15F8F2941C96.ogg__codecs_opus",
    "filename": "false_972507735297@c.us_DAD4FA7BAF0BF546398F15F8F2941C96.ogg__codecs_opus",
    "description": "קובץ מדיה שהתקבל מהמשתמש (דיצה)",
    "type": "audio/ogg; codecs=opus"
  },
  {
    "timestamp": "2025-07-01T20:17:25.242Z",
    "originalMessageId": "true_972507735297@c.us_1E59EF2E9ABDC467B474538200A4A6AF",
    "generatedFilePath": "C:\\Users\\hillel1\\Desktop\\WHAT\\chats/972507735297_דיצה/files/true_972507735297@c.us_1E59EF2E9ABDC467B474538200A4A6AF.jpeg",
    "filename": "true_972507735297@c.us_1E59EF2E9ABDC467B474538200A4A6AF.jpeg",
    "description": "קובץ מדיה שהתקבל מהמשתמש (הלל (Owner))",
    "type": "image/jpeg"
  },
  {
    "timestamp": "2025-07-01T20:19:59.279Z",
    "originalMessageId": "false_972507735297@c.us_1029AD8F85F3AC448875325BD2FE76C8",
    "generatedFilePath": "C:\\Users\\hillel1\\Desktop\\WHAT\\chats/972507735297_דיצה/files/false_972507735297@c.us_1029AD8F85F3AC448875325BD2FE76C8.ogg__codecs_opus",
    "filename": "false_972507735297@c.us_1029AD8F85F3AC448875325BD2FE76C8.ogg__codecs_opus",
    "description": "קובץ מדיה שהתקבל מהמשתמש (דיצה)",
    "type": "audio/ogg; codecs=opus"
  },
  {
    "timestamp": "2025-07-01T20:20:28.518Z",
    "originalMessageId": "false_972507735297@c.us_A1477170551B4877D4DDD313205A11D1",
    "generatedFilePath": "C:\\Users\\hillel1\\Desktop\\WHAT\\chats/972507735297_דיצה/files/false_972507735297@c.us_A1477170551B4877D4DDD313205A11D1.ogg__codecs_opus",
    "filename": "false_972507735297@c.us_A1477170551B4877D4DDD313205A11D1.ogg__codecs_opus",
    "description": "קובץ מדיה שהתקבל מהמשתמש (דיצה)",
    "type": "audio/ogg; codecs=opus"
  },
  {
    "timestamp": "2025-07-01T20:45:35.873Z",
    "originalMessageId": "false_972507735297@c.us_5E09B543360AB832CF884D4D30E43727",
    "generatedFilePath": "C:\\Users\\hillel1\\Desktop\\WHAT\\chats/972507735297_דיצה/files/false_972507735297@c.us_5E09B543360AB832CF884D4D30E43727.jpeg",
    "filename": "false_972507735297@c.us_5E09B543360AB832CF884D4D30E43727.jpeg",
    "description": "קובץ מדיה שהתקבל מהמשתמש (דיצה)",
    "type": "image/jpeg"
  },
  {
    "timestamp": "2025-07-01T20:46:32.151Z",
    "originalMessageId": "true_972507735297@c.us_F6B42B853ED46751B3F3A37C3E76DA36",
    "generatedFilePath": "C:\\Users\\hillel1\\Desktop\\WHAT\\chats/972507735297_דיצה/files/true_972507735297@c.us_F6B42B853ED46751B3F3A37C3E76DA36.jpeg",
    "filename": "true_972507735297@c.us_F6B42B853ED46751B3F3A37C3E76DA36.jpeg",
    "description": "קובץ מדיה שהתקבל מהמשתמש (הלל (Owner))",
    "type": "image/jpeg"
  },
  {
    "timestamp": "2025-07-01T20:47:38.752Z",
    "originalMessageId": "false_972507735297@c.us_D143F5AA22E92326444EE58F727B3F23",
    "generatedFilePath": "C:\\Users\\hillel1\\Desktop\\WHAT\\chats/972507735297_דיצה/files/false_972507735297@c.us_D143F5AA22E92326444EE58F727B3F23.jpeg",
    "filename": "false_972507735297@c.us_D143F5AA22E92326444EE58F727B3F23.jpeg",
    "description": "קובץ מדיה שהתקבל מהמשתמש (דיצה)",
    "type": "image/jpeg"
  }
]