[
  {
    "timestamp": "2025-07-02T14:07:08.371Z",
    "originalMessageId": "true_972535230984@c.us_48872835D4363EDDFF4978DDDCC94B6F",
    "generatedFilePath": "C:\\Users\\hillel1\\Desktop\\WHAT\\chats/972535230984_Dvir/files/true_972535230984@c.us_48872835D4363EDDFF4978DDDCC94B6F.jpeg",
    "filename": "true_972535230984@c.us_48872835D4363EDDFF4978DDDCC94B6F.jpeg",
    "description": "קובץ מדיה שהתקבל מהמשתמש (הלל (Owner))",
    "type": "image/jpeg"
  },
  {
    "timestamp": "2025-07-05T19:16:57.343Z",
    "originalMessageId": "false_972535230984@c.us_3F7838657A850D657F88",
    "generatedFilePath": "C:\\Users\\hillel1\\Desktop\\WHAT\\chats/972535230984_Dvir/files/false_972535230984@c.us_3F7838657A850D657F88.jpeg",
    "filename": "false_972535230984@c.us_3F7838657A850D657F88.jpeg",
    "description": "קובץ מדיה שהתקבל מהמשתמש (Dvir)",
    "type": "image/jpeg"
  }
]